{
  "name": "Explode",
  "category": "Interactions",
  "properties": [],
  "inputs": [
    { "name": "connector", "type": "connector" },
    { "name": "Level <Level>", "type": "level" },
    { "name": "X <Number>", "type": "number" },
    { "name": "Y <Number>", "type": "number" },
    { "name": "Z <Number>", "type": "number" },
    { "name": "Radius <Number>", "type": "number" },
    { "name": "With Fire? <Boolean>", "type": "boolean" },
    { "name": "Destroy Blocks? <Boolean>", "type": "boolean" }
  ],
  "outputs": [{ "name": "connector", "type": "connector" }],
  "showInContext": true,
  "plugin": "Explode"
}
